emcaps/__init__.py
emcaps/_version.py
emcaps/class_info.yaml
emcaps/model_registry.yaml
emcaps/analysis/__init__.py
emcaps/analysis/averagepatches.py
emcaps/analysis/cf_matrix.py
emcaps/analysis/encari.py
emcaps/analysis/size_analysis.py
emcaps/conf/__init__.py
emcaps/conf/config.yaml
emcaps/inference/__init__.py
emcaps/inference/patcheval.py
emcaps/inference/patchifyseg.py
emcaps/inference/segment.py
emcaps/models/__init__.py
emcaps/models/effnetv2.py
emcaps/training/__init__.py
emcaps/training/emcdata.py
emcaps/training/patchtrain.py
emcaps/training/segtrain.py
emcaps/utils/__init__.py
emcaps/utils/colorlabel.py
emcaps/utils/inference_utils.py
emcaps/utils/patch_utils.py
emcaps/utils/splitdataset.py
emcaps/utils/utils.py
emcaps-1.0.0.dist-info/LICENSE
emcaps-1.0.0.dist-info/METADATA
emcaps-1.0.0.dist-info/WHEEL
emcaps-1.0.0.dist-info/entry_points.txt
emcaps-1.0.0.dist-info/top_level.txt
emcaps-1.0.0.dist-info/RECORD
