Metadata-Version: 2.1
Name: emcaps
Version: 1.0.0
Summary: Code for the paper Genetically encoded barcodes for correlative volume electron microscopy
License: MIT License
Keywords: emcapsulin,encapsulin
Classifier: Programming Language :: Python :: 3
Classifier: License :: OSI Approved :: MIT License
Classifier: Topic :: Scientific/Engineering :: Image Processing
Classifier: Topic :: Scientific/Engineering :: Image Recognition
Requires-Python: >=3.10
License-File: LICENSE
Requires-Dist: elektronn3 (<0.2.0,>=0.1.0)
Requires-Dist: albumentations (>=1.0.3)
Requires-Dist: hydra-core (>=1.2.0)
Requires-Dist: imageio (>=2.19.3)
Requires-Dist: ipython (>=8.4.0)
Requires-Dist: matplotlib (>=3.5.2)
Requires-Dist: numpy (>=1.22.4)
Requires-Dist: omegaconf (>=2.2.1)
Requires-Dist: pandas (>=1.4.3)
Requires-Dist: Pillow (>=9.1.1)
Requires-Dist: PyYAML (>=6.0)
Requires-Dist: scikit-image (>=0.19.3)
Requires-Dist: scikit-learn (>=1.1.1)
Requires-Dist: scipy (>=1.8.1)
Requires-Dist: seaborn (>=0.11.2)
Requires-Dist: setuptools (>=62.6.0)
Requires-Dist: torch (>=1.12.1)
Requires-Dist: tqdm (>=4.64.0)
Requires-Dist: typing-extensions (>=4.2.0)
Requires-Dist: ubelt (>=1.1.2)
Requires-Dist: openpyxl (>=3.0)
Requires-Dist: magicgui (>=0.5.1)
Requires-Dist: napari (>=0.4.16)
